nestipy_prisma/__init__.py
nestipy_prisma/prisma_builder.py
nestipy_prisma/prisma_module.py
nestipy_prisma/prisma_service.py
nestipy_prisma-0.1.2.dist-info/LICENSE
nestipy_prisma-0.1.2.dist-info/METADATA
nestipy_prisma-0.1.2.dist-info/WHEEL
nestipy_prisma-0.1.2.dist-info/RECORD
