Metadata-Version: 2.1
Name: nestipy-prisma
Version: 0.1.2
Summary: 
Author: tsiresymila
Author-email: tsiresymila@gmail.com
Requires-Python: >=3.11,<4.0
Classifier: Programming Language :: Python :: 3
Classifier: Programming Language :: Python :: 3.11
Classifier: Programming Language :: Python :: 3.12
Requires-Dist: prisma (>=0.13.1,<0.14.0)
